{"data":[{"campaign_id":"120225384083980176","campaign_name":"03-06 RECONHECIMENTO","impressions":"31277","clicks":"58","spend":"66.68","cpc":"1.149655","cpm":"2.131918","ctr":"0.18544","reach":"17718","frequency":"1.765267","actions":[{"action_type":"link_click","value":"15"},{"action_type":"page_engagement","value":"1560"},{"action_type":"post_interaction_gross","value":"20"},{"action_type":"post","value":"1"},{"action_type":"post_engagement","value":"1560"},{"action_type":"onsite_conversion.post_net_like","value":"19"},{"action_type":"video_view","value":"1525"},{"action_type":"post_reaction","value":"19"}],"cost_per_action_type":[{"action_type":"video_view","value":"0.043725"},{"action_type":"link_click","value":"4.445333"},{"action_type":"post_interaction_gross","value":"3.334"},{"action_type":"post_engagement","value":"0.042744"},{"action_type":"page_engagement","value":"0.042744"}],"date_start":"2025-06-02","date_stop":"2025-06-30"},{"campaign_id":"120225860437260176","campaign_name":"CBO 10-06 CLICKS VENDAS","impressions":"7146","clicks":"79","spend":"78.07","cpc":"0.988228","cpm":"10.924993","ctr":"1.105514","reach":"3074","frequency":"2.324658","actions":[{"action_type":"onsite_conversion.total_messaging_connection","value":"6"},{"action_type":"link_click","value":"20"},{"action_type":"page_engagement","value":"841"},{"action_type":"comment","value":"1"},{"action_type":"post_interaction_gross","value":"20"},{"action_type":"onsite_conversion.messaging_user_depth_2_message_send","value":"5"},{"action_type":"onsite_conversion.messaging_first_reply","value":"7"},{"action_type":"post","value":"6"},{"action_type":"onsite_conversion.messaging_user_depth_3_message_send","value":"3"},{"action_type":"post_engagement","value":"841"},{"action_type":"onsite_conversion.post_net_like","value":"13"},{"action_type":"onsite_conversion.messaging_conversation_started_7d","value":"9"},{"action_type":"video_view","value":"801"},{"action_type":"post_reaction","value":"13"}],"cost_per_action_type":[{"action_type":"onsite_conversion.total_messaging_connection","value":"13.011667"},{"action_type":"video_view","value":"0.097466"},{"action_type":"link_click","value":"3.9035"},{"action_type":"post_interaction_gross","value":"3.9035"},{"action_type":"onsite_conversion.messaging_user_depth_2_message_send","value":"15.614"},{"action_type":"onsite_conversion.messaging_user_depth_3_message_send","value":"26.023333"},{"action_type":"post_engagement","value":"0.09283"},{"action_type":"page_engagement","value":"0.09283"},{"action_type":"onsite_conversion.messaging_first_reply","value":"11.152857"},{"action_type":"onsite_conversion.messaging_conversation_started_7d","value":"8.674444"}],"date_start":"2025-06-02","date_stop":"2025-06-30"},{"campaign_id":"120226505008610176","campaign_name":"CBO 17-06 CLICKS VENDAs","impressions":"3160","clicks":"31","spend":"27.5","cpc":"0.887097","cpm":"8.702532","ctr":"0.981013","reach":"1927","frequency":"1.639855","actions":[{"action_type":"onsite_conversion.total_messaging_connection","value":"3"},{"action_type":"link_click","value":"7"},{"action_type":"page_engagement","value":"382"},{"action_type":"post_interaction_gross","value":"11"},{"action_type":"onsite_conversion.messaging_user_depth_2_message_send","value":"2"},{"action_type":"onsite_conversion.messaging_first_reply","value":"3"},{"action_type":"post","value":"1"},{"action_type":"onsite_conversion.messaging_user_depth_3_message_send","value":"2"},{"action_type":"post_engagement","value":"382"},{"action_type":"onsite_conversion.post_net_like","value":"10"},{"action_type":"onsite_conversion.messaging_conversation_started_7d","value":"3"},{"action_type":"video_view","value":"364"},{"action_type":"post_reaction","value":"10"}],"cost_per_action_type":[{"action_type":"onsite_conversion.total_messaging_connection","value":"9.166667"},{"action_type":"video_view","value":"0.075549"},{"action_type":"link_click","value":"3.928571"},{"action_type":"post_interaction_gross","value":"2.5"},{"action_type":"onsite_conversion.messaging_user_depth_2_message_send","value":"13.75"},{"action_type":"onsite_conversion.messaging_user_depth_3_message_send","value":"13.75"},{"action_type":"post_engagement","value":"0.07199"},{"action_type":"page_engagement","value":"0.07199"},{"action_type":"onsite_conversion.messaging_first_reply","value":"9.166667"},{"action_type":"onsite_conversion.messaging_conversation_started_7d","value":"9.166667"}],"date_start":"2025-06-02","date_stop":"2025-06-30"},{"campaign_id":"120227410506700176","campaign_name":"01-07 CBO MSG LEDS","impressions":"6963","clicks":"72","spend":"62.7","cpc":"0.870833","cpm":"9.004739","ctr":"1.034037","reach":"3406","frequency":"2.044334","actions":[{"action_type":"onsite_conversion.total_messaging_connection","value":"8"},{"action_type":"link_click","value":"16"},{"action_type":"page_engagement","value":"1316"},{"action_type":"post_interaction_gross","value":"39"},{"action_type":"onsite_conversion.messaging_user_depth_2_message_send","value":"7"},{"action_type":"onsite_conversion.messaging_first_reply","value":"9"},{"action_type":"onsite_conversion.post_save","value":"1"},{"action_type":"onsite_conversion.messaging_user_depth_3_message_send","value":"5"},{"action_type":"post_engagement","value":"1316"},{"action_type":"onsite_conversion.post_net_like","value":"38"},{"action_type":"onsite_conversion.post_net_save","value":"1"},{"action_type":"onsite_conversion.messaging_conversation_started_7d","value":"11"},{"action_type":"video_view","value":"1261"},{"action_type":"post_reaction","value":"38"}],"cost_per_action_type":[{"action_type":"onsite_conversion.total_messaging_connection","value":"7.8375"},{"action_type":"video_view","value":"0.049722"},{"action_type":"link_click","value":"3.91875"},{"action_type":"post_interaction_gross","value":"1.607692"},{"action_type":"onsite_conversion.messaging_user_depth_2_message_send","value":"8.957143"},{"action_type":"onsite_conversion.messaging_user_depth_3_message_send","value":"12.54"},{"action_type":"post_engagement","value":"0.047644"},{"action_type":"page_engagement","value":"0.047644"},{"action_type":"onsite_conversion.messaging_first_reply","value":"6.966667"},{"action_type":"onsite_conversion.messaging_conversation_started_7d","value":"5.7"}],"date_start":"2025-07-01","date_stop":"2025-07-31"},{"campaign_id":"120227798412690176","campaign_name":"01-07 CBO MSG LEDS \u2014 C\u00f3pia","impressions":"6851","clicks":"72","spend":"65.05","cpc":"0.903472","cpm":"9.494964","ctr":"1.050941","reach":"3548","frequency":"1.930947","actions":[{"action_type":"onsite_conversion.total_messaging_connection","value":"11"},{"action_type":"link_click","value":"24"},{"action_type":"page_engagement","value":"1182"},{"action_type":"comment","value":"2"},{"action_type":"like","value":"1"},{"action_type":"post_interaction_gross","value":"23"},{"action_type":"onsite_conversion.messaging_user_depth_2_message_send","value":"9"},{"action_type":"onsite_conversion.messaging_first_reply","value":"11"},{"action_type":"onsite_conversion.messaging_user_depth_3_message_send","value":"8"},{"action_type":"post_engagement","value":"1181"},{"action_type":"onsite_conversion.post_net_like","value":"21"},{"action_type":"onsite_conversion.messaging_conversation_started_7d","value":"11"},{"action_type":"video_view","value":"1134"},{"action_type":"post_reaction","value":"21"}],"cost_per_action_type":[{"action_type":"onsite_conversion.total_messaging_connection","value":"5.913636"},{"action_type":"video_view","value":"0.057363"},{"action_type":"link_click","value":"2.710417"},{"action_type":"like","value":"65.05"},{"action_type":"post_interaction_gross","value":"2.828261"},{"action_type":"onsite_conversion.messaging_user_depth_2_message_send","value":"7.227778"},{"action_type":"onsite_conversion.messaging_user_depth_3_message_send","value":"8.13125"},{"action_type":"post_engagement","value":"0.05508"},{"action_type":"page_engagement","value":"0.055034"},{"action_type":"onsite_conversion.messaging_first_reply","value":"5.913636"},{"action_type":"onsite_conversion.messaging_conversation_started_7d","value":"5.913636"}],"date_start":"2025-07-01","date_stop":"2025-07-31"},{"campaign_id":"120230272696690176","campaign_name":"CBO-15-08-MSG","impressions":"7202","clicks":"86","spend":"71.68","cpc":"0.833488","cpm":"9.952791","ctr":"1.194113","reach":"3418","frequency":"2.10708","actions":[{"action_type":"onsite_conversion.total_messaging_connection","value":"10"},{"action_type":"link_click","value":"24"},{"action_type":"page_engagement","value":"1080"},{"action_type":"comment","value":"1"},{"action_type":"like","value":"2"},{"action_type":"post_interaction_gross","value":"28"},{"action_type":"onsite_conversion.messaging_user_depth_2_message_send","value":"7"},{"action_type":"onsite_conversion.messaging_first_reply","value":"9"},{"action_type":"post","value":"4"},{"action_type":"onsite_conversion.messaging_user_depth_3_message_send","value":"4"},{"action_type":"post_engagement","value":"1078"},{"action_type":"onsite_conversion.post_net_like","value":"23"},{"action_type":"onsite_conversion.messaging_conversation_started_7d","value":"10"},{"action_type":"video_view","value":"1026"},{"action_type":"post_reaction","value":"23"}],"cost_per_action_type":[{"action_type":"onsite_conversion.total_messaging_connection","value":"7.168"},{"action_type":"video_view","value":"0.069864"},{"action_type":"link_click","value":"2.986667"},{"action_type":"like","value":"35.84"},{"action_type":"post_interaction_gross","value":"2.56"},{"action_type":"onsite_conversion.messaging_user_depth_2_message_send","value":"10.24"},{"action_type":"onsite_conversion.messaging_user_depth_3_message_send","value":"17.92"},{"action_type":"post_engagement","value":"0.066494"},{"action_type":"page_engagement","value":"0.06637"},{"action_type":"onsite_conversion.messaging_first_reply","value":"7.964444"},{"action_type":"onsite_conversion.messaging_conversation_started_7d","value":"7.168"}],"date_start":"2025-08-01","date_stop":"2025-08-31"},{"campaign_id":"120230652911460176","campaign_name":"ABO-22-08-MSG","impressions":"4263","clicks":"73","spend":"50.19","cpc":"0.687534","cpm":"11.773399","ctr":"1.712409","reach":"2274","frequency":"1.87467","actions":[{"action_type":"onsite_conversion.total_messaging_connection","value":"4"},{"action_type":"link_click","value":"27"},{"action_type":"page_engagement","value":"723"},{"action_type":"comment","value":"3"},{"action_type":"post_interaction_gross","value":"33"},{"action_type":"onsite_conversion.messaging_user_depth_2_message_send","value":"2"},{"action_type":"onsite_conversion.messaging_first_reply","value":"2"},{"action_type":"post","value":"3"},{"action_type":"onsite_conversion.messaging_user_depth_3_message_send","value":"2"},{"action_type":"post_engagement","value":"723"},{"action_type":"onsite_conversion.post_net_like","value":"27"},{"action_type":"onsite_conversion.messaging_conversation_started_7d","value":"4"},{"action_type":"video_view","value":"663"},{"action_type":"post_reaction","value":"27"}],"cost_per_action_type":[{"action_type":"onsite_conversion.total_messaging_connection","value":"12.5475"},{"action_type":"video_view","value":"0.075701"},{"action_type":"link_click","value":"1.858889"},{"action_type":"post_interaction_gross","value":"1.520909"},{"action_type":"onsite_conversion.messaging_user_depth_2_message_send","value":"25.095"},{"action_type":"onsite_conversion.messaging_user_depth_3_message_send","value":"25.095"},{"action_type":"post_engagement","value":"0.069419"},{"action_type":"page_engagement","value":"0.069419"},{"action_type":"onsite_conversion.messaging_first_reply","value":"25.095"},{"action_type":"onsite_conversion.messaging_conversation_started_7d","value":"12.5475"}],"date_start":"2025-08-01","date_stop":"2025-08-31"},{"campaign_id":"120230908476130176","campaign_name":"CBO - VENDAS - WPP - 27\/08","impressions":"5569","clicks":"104","spend":"92.07","cpc":"0.885288","cpm":"16.532591","ctr":"1.867481","reach":"3180","frequency":"1.751258","actions":[{"action_type":"onsite_conversion.total_messaging_connection","value":"12"},{"action_type":"link_click","value":"29"},{"action_type":"page_engagement","value":"1078"},{"action_type":"comment","value":"1"},{"action_type":"like","value":"1"},{"action_type":"post_interaction_gross","value":"26"},{"action_type":"onsite_conversion.messaging_user_depth_2_message_send","value":"6"},{"action_type":"onsite_conversion.messaging_first_reply","value":"10"},{"action_type":"post","value":"2"},{"action_type":"onsite_conversion.post_save","value":"1"},{"action_type":"onsite_conversion.messaging_user_depth_3_message_send","value":"3"},{"action_type":"post_engagement","value":"1077"},{"action_type":"onsite_conversion.post_net_like","value":"22"},{"action_type":"onsite_conversion.post_net_save","value":"1"},{"action_type":"onsite_conversion.messaging_conversation_started_7d","value":"11"},{"action_type":"video_view","value":"1022"},{"action_type":"post_reaction","value":"22"}],"cost_per_action_type":[{"action_type":"onsite_conversion.total_messaging_connection","value":"7.6725"},{"action_type":"video_view","value":"0.090088"},{"action_type":"link_click","value":"3.174828"},{"action_type":"like","value":"92.07"},{"action_type":"post_interaction_gross","value":"3.541154"},{"action_type":"onsite_conversion.messaging_user_depth_2_message_send","value":"15.345"},{"action_type":"onsite_conversion.messaging_user_depth_3_message_send","value":"30.69"},{"action_type":"post_engagement","value":"0.085487"},{"action_type":"page_engagement","value":"0.085408"},{"action_type":"onsite_conversion.messaging_first_reply","value":"9.207"},{"action_type":"onsite_conversion.messaging_conversation_started_7d","value":"8.37"}],"date_start":"2025-08-01","date_stop":"2025-08-31"},{"campaign_id":"120230908476130176","campaign_name":"CBO - VENDAS - WPP - 27\/08","impressions":"16684","clicks":"307","spend":"286.06","cpc":"0.931792","cpm":"17.145768","ctr":"1.840086","reach":"6650","frequency":"2.508872","actions":[{"action_type":"onsite_conversion.total_messaging_connection","value":"62"},{"action_type":"link_click","value":"94"},{"action_type":"page_engagement","value":"3092"},{"action_type":"like","value":"2"},{"action_type":"post_interaction_gross","value":"52"},{"action_type":"onsite_conversion.messaging_user_depth_2_message_send","value":"41"},{"action_type":"onsite_conversion.messaging_first_reply","value":"50"},{"action_type":"post","value":"2"},{"action_type":"onsite_conversion.messaging_user_depth_3_message_send","value":"35"},{"action_type":"post_engagement","value":"3090"},{"action_type":"onsite_conversion.post_net_like","value":"50"},{"action_type":"onsite_conversion.messaging_conversation_started_7d","value":"52"},{"action_type":"video_view","value":"2944"},{"action_type":"post_reaction","value":"50"}],"cost_per_action_type":[{"action_type":"onsite_conversion.total_messaging_connection","value":"4.613871"},{"action_type":"video_view","value":"0.097167"},{"action_type":"link_click","value":"3.043191"},{"action_type":"like","value":"143.03"},{"action_type":"post_interaction_gross","value":"5.501154"},{"action_type":"onsite_conversion.messaging_user_depth_2_message_send","value":"6.977073"},{"action_type":"onsite_conversion.messaging_user_depth_3_message_send","value":"8.173143"},{"action_type":"post_engagement","value":"0.092576"},{"action_type":"page_engagement","value":"0.092516"},{"action_type":"onsite_conversion.messaging_first_reply","value":"5.7212"},{"action_type":"onsite_conversion.messaging_conversation_started_7d","value":"5.501154"}],"date_start":"2025-09-01","date_stop":"2025-09-30"},{"campaign_id":"120230908476130176","campaign_name":"CBO - VENDAS - WPP - 27\/08","impressions":"15941","clicks":"297","spend":"287.11","cpc":"0.9667","cpm":"18.01079","ctr":"1.86312","reach":"7630","frequency":"2.089253","actions":[{"action_type":"onsite_conversion.total_messaging_connection","value":"48"},{"action_type":"link_click","value":"84"},{"action_type":"page_engagement","value":"3161"},{"action_type":"comment","value":"4"},{"action_type":"like","value":"3"},{"action_type":"post_interaction_gross","value":"81"},{"action_type":"onsite_conversion.messaging_user_depth_2_message_send","value":"26"},{"action_type":"onsite_conversion.messaging_first_reply","value":"43"},{"action_type":"post","value":"7"},{"action_type":"onsite_conversion.post_save","value":"1"},{"action_type":"onsite_conversion.messaging_user_depth_3_message_send","value":"11"},{"action_type":"post_engagement","value":"3158"},{"action_type":"onsite_conversion.post_net_like","value":"69"},{"action_type":"onsite_conversion.post_net_save","value":"1"},{"action_type":"onsite_conversion.messaging_conversation_started_7d","value":"45"},{"action_type":"video_view","value":"2993"},{"action_type":"post_reaction","value":"69"}],"cost_per_action_type":[{"action_type":"onsite_conversion.total_messaging_connection","value":"5.981458"},{"action_type":"video_view","value":"0.095927"},{"action_type":"link_click","value":"3.417976"},{"action_type":"like","value":"95.703333"},{"action_type":"post_interaction_gross","value":"3.544568"},{"action_type":"onsite_conversion.messaging_user_depth_2_message_send","value":"11.042692"},{"action_type":"onsite_conversion.messaging_user_depth_3_message_send","value":"26.100909"},{"action_type":"post_engagement","value":"0.090915"},{"action_type":"page_engagement","value":"0.090829"},{"action_type":"onsite_conversion.messaging_first_reply","value":"6.676977"},{"action_type":"onsite_conversion.messaging_conversation_started_7d","value":"6.380222"}],"date_start":"2025-11-01","date_stop":"2025-11-30"},{"campaign_id":"120235169548040176","campaign_name":"CBO - SORTEIO - LEADS - WPP - 09-11","impressions":"11344","clicks":"102","spend":"212.89","cpc":"2.087157","cpm":"18.766749","ctr":"0.899154","reach":"5057","frequency":"2.243227","actions":[{"action_type":"onsite_conversion.total_messaging_connection","value":"11"},{"action_type":"link_click","value":"53"},{"action_type":"page_engagement","value":"1279"},{"action_type":"post_interaction_gross","value":"28"},{"action_type":"onsite_conversion.messaging_user_depth_2_message_send","value":"7"},{"action_type":"onsite_conversion.messaging_first_reply","value":"11"},{"action_type":"onsite_conversion.post_save","value":"2"},{"action_type":"onsite_conversion.messaging_user_depth_3_message_send","value":"3"},{"action_type":"post_engagement","value":"1279"},{"action_type":"onsite_conversion.post_net_like","value":"26"},{"action_type":"onsite_conversion.post_net_save","value":"2"},{"action_type":"onsite_conversion.messaging_conversation_started_7d","value":"11"},{"action_type":"video_view","value":"1198"},{"action_type":"post_reaction","value":"26"}],"cost_per_action_type":[{"action_type":"onsite_conversion.total_messaging_connection","value":"19.353636"},{"action_type":"video_view","value":"0.177705"},{"action_type":"link_click","value":"4.016792"},{"action_type":"post_interaction_gross","value":"7.603214"},{"action_type":"onsite_conversion.messaging_user_depth_2_message_send","value":"30.412857"},{"action_type":"onsite_conversion.messaging_user_depth_3_message_send","value":"70.963333"},{"action_type":"post_engagement","value":"0.16645"},{"action_type":"page_engagement","value":"0.16645"},{"action_type":"onsite_conversion.messaging_first_reply","value":"19.353636"},{"action_type":"onsite_conversion.messaging_conversation_started_7d","value":"19.353636"}],"date_start":"2025-11-01","date_stop":"2025-11-30"}],"paging":{"cursors":{"before":"MAZDZD","after":"MTAZD"}}}
